embellish_folder/__init__.py
embellish_folder/__main__.py
embellish_folder/api.py
embellish_folder/app.py
embellish_folder/base_icons.py
embellish_folder/cli.py
embellish_folder/fileicon.py
embellish_folder/read.py
embellish_folder/version.py
embellish_folder/write.py
embellish_folder-0.11.0.dist-info/LICENSE.txt
embellish_folder-0.11.0.dist-info/METADATA
embellish_folder-0.11.0.dist-info/WHEEL
embellish_folder-0.11.0.dist-info/top_level.txt
embellish_folder-0.11.0.dist-info/zip-safe
embellish_folder-0.11.0.dist-info/RECORD
