Metadata-Version: 2.1
Name: embellish-folder
Version: 0.11.0
Summary: Embellish a folder icon
Home-page: https://github.com/sixty-north/embellish_folder
Author: Sixty North AS
Author-email: systems+embellish_folder@sixty-north.com
License: MIT License
Keywords: icons
Classifier: Development Status :: 5 - Production/Stable
Classifier: Intended Audience :: Developers
Classifier: Topic :: Software Development :: Libraries :: Python Modules
Classifier: License :: OSI Approved :: MIT License
Classifier: Programming Language :: Python :: 3 :: Only
Classifier: Programming Language :: Python :: 3.10
Classifier: Programming Language :: Python :: 3.11
License-File: LICENSE.txt
Requires-Dist: appdirs
Requires-Dist: click
Requires-Dist: exit-codes
Requires-Dist: pillow
Provides-Extra: dev
Requires-Dist: bumpversion ; extra == 'dev'
Provides-Extra: doc
Requires-Dist: sphinx ; extra == 'doc'
Requires-Dist: sphinx-rtd-theme ; extra == 'doc'
Requires-Dist: better-apidoc ; extra == 'doc'
Provides-Extra: test
Requires-Dist: pytest ; extra == 'test'
